assistant_ui/__init__.py
assistant_ui/client.py
assistant_ui/types.py
assistant_ui_sync_server_api-0.1.1.dist-info/METADATA
assistant_ui_sync_server_api-0.1.1.dist-info/WHEEL
assistant_ui_sync_server_api-0.1.1.dist-info/licenses/LICENSE
assistant_ui_sync_server_api-0.1.1.dist-info/RECORD
