Metadata-Version: 2.4
Name: assistant-ui-sync-server-api
Version: 0.1.1
Summary: Python client for Assistant UI sync server API
Project-URL: Homepage, https://github.com/assistant-ui/assistant-ui
Project-URL: Issues, https://github.com/assistant-ui/assistant-ui/issues
Project-URL: Documentation, https://docs.assistant-ui.com
Author-email: Assistant UI Team <team@assistant-ui.com>
License-File: LICENSE
Classifier: Development Status :: 3 - Alpha
Classifier: Intended Audience :: Developers
Classifier: License :: OSI Approved :: MIT License
Classifier: Operating System :: OS Independent
Classifier: Programming Language :: Python :: 3
Classifier: Topic :: Software Development :: Libraries :: Python Modules
Requires-Python: >=3.8
Requires-Dist: httpx>=0.24.0
Requires-Dist: typing-extensions>=4.0.0; python_full_version < '3.11'
Provides-Extra: dev
Requires-Dist: black>=23.0.0; extra == 'dev'
Requires-Dist: isort>=5.0.0; extra == 'dev'
Requires-Dist: mypy>=1.0.0; extra == 'dev'
Requires-Dist: pytest-asyncio>=0.21.0; extra == 'dev'
Requires-Dist: pytest>=7.0.0; extra == 'dev'
